python_runner/__init__.py
python_runner/output.py
python_runner/runner.py
python_runner/snoop.py
python_runner/version.py
python_runner-0.6.1.dist-info/LICENSE.txt
python_runner-0.6.1.dist-info/METADATA
python_runner-0.6.1.dist-info/WHEEL
python_runner-0.6.1.dist-info/top_level.txt
python_runner-0.6.1.dist-info/RECORD
