Metadata-Version: 2.1
Name: python-runner
Version: 0.6.1
Summary: Helper for running python code indirectly
Home-page: http://github.com/alexmojaki/python_runner
Author: Alex Hall
Author-email: alex.mojaki@gmail.com
License: MIT
Classifier: Intended Audience :: Developers
Classifier: Programming Language :: Python :: 3.8
Classifier: Programming Language :: Python :: 3.9
Classifier: Programming Language :: Python :: 3.10
Classifier: License :: OSI Approved :: MIT License
Classifier: Operating System :: OS Independent
Provides-Extra: tests
License-File: LICENSE.txt
